odoo8_addon_mis_builder_analytic_filter-8.0.1.0.0.99.dev10-py2.7-nspkg.pth
odoo8_addon_mis_builder_analytic_filter-8.0.1.0.0.99.dev10.dist-info/METADATA
odoo8_addon_mis_builder_analytic_filter-8.0.1.0.0.99.dev10.dist-info/RECORD
odoo8_addon_mis_builder_analytic_filter-8.0.1.0.0.99.dev10.dist-info/WHEEL
odoo8_addon_mis_builder_analytic_filter-8.0.1.0.0.99.dev10.dist-info/namespace_packages.txt
odoo8_addon_mis_builder_analytic_filter-8.0.1.0.0.99.dev10.dist-info/top_level.txt
odoo_addons/mis_builder_analytic_filter/README.rst
odoo_addons/mis_builder_analytic_filter/__init__.py
odoo_addons/mis_builder_analytic_filter/__openerp__.py
odoo_addons/mis_builder_analytic_filter/i18n/mis_builder_analytic_filter.pot
odoo_addons/mis_builder_analytic_filter/i18n/sl.po
odoo_addons/mis_builder_analytic_filter/models/__init__.py
odoo_addons/mis_builder_analytic_filter/models/mis_report.py
odoo_addons/mis_builder_analytic_filter/static/description/icon.png
odoo_addons/mis_builder_analytic_filter/static/src/js/mis_builder.js
odoo_addons/mis_builder_analytic_filter/static/src/xml/mis_widget.xml
odoo_addons/mis_builder_analytic_filter/views/mis_builder_analytic.xml
odoo_addons/mis_builder_analytic_filter/views/mis_report_view.xml
